Metadata-Version: 2.4
Name: openimis-be-tools
Version: 1.10.0
Summary: The openIMIS Backend Tools reference module.
Home-page: https://openimis.org/
Author: Bluesquare
Author-email: developers@bluesquare.org
License: GNU AGPL v3
Classifier: Environment :: Web Environment
Classifier: Framework :: Django
Classifier: Framework :: Django :: 2.1
Classifier: Intended Audience :: Developers
Classifier: License :: OSI Approved :: GNU Affero General Public License v3
Classifier: Operating System :: OS Independent
Classifier: Programming Language :: Python
Classifier: Programming Language :: Python :: 3.6
Classifier: Programming Language :: Python :: 3.7
Classifier: Programming Language :: Python :: 3.8
License-File: LICENSE.md
Requires-Dist: django
Requires-Dist: django-db-signals
Requires-Dist: djangorestframework
Requires-Dist: djangorestframework-xml
Requires-Dist: simplejson
Requires-Dist: pyminizip
Requires-Dist: pyzipper
Requires-Dist: defusedxml
Requires-Dist: tablib
Requires-Dist: django-import-export
Dynamic: author
Dynamic: author-email
Dynamic: classifier
Dynamic: home-page
Dynamic: license
Dynamic: license-file
Dynamic: requires-dist
Dynamic: summary
